{"cameraMode":{"drawMode":0,"name":"Shaded","section":"Shading Mode"},"sceneLighting":true,"audioPlay":false,"sceneViewState":{"showFog":true,"showMaterialUpdate":false,"showSkybox":true,"showFlares":true,"showImageEffects":true,"showParticleSystems":true},"in2DMode":false,"pivot":{"x":139.6013641357422,"y":5.046142578125,"z":109.44664001464844},"rotation":{"x":-0.20331251621246339,"y":0.18379533290863038,"z":-0.038871485739946368,"w":-0.9609328508377075},"size":574.4559936523438,"orthographic":false}